LICENSE
README.md
setup.py
simplarchiver/__init__.py
simplarchiver/abc.py
simplarchiver/controller.py
simplarchiver/node.py
simplarchiver/pair.py
simplarchiver/update.py
simplarchiver.egg-info/PKG-INFO
simplarchiver.egg-info/SOURCES.txt
simplarchiver.egg-info/dependency_links.txt
simplarchiver.egg-info/top_level.txt
simplarchiver/example/__init__.py
simplarchiver/example/exception.py
simplarchiver/example/just.py
simplarchiver/example/random.py
simplarchiver/example/sleep.py
simplarchiver/example/subprocess.py
simplarchiver/example/file/__init__.py
simplarchiver/example/file/file.py
simplarchiver/example/file/update.py
simplarchiver/example/qbittorrent/__init__.py
simplarchiver/example/qbittorrent/qbittorrent.py
simplarchiver/example/rss/__init__.py
simplarchiver/example/rss/common.py
simplarchiver/example/rss/filter.py
simplarchiver/example/rss/rsshub.py
simplarchiver/example/rss/ttrss.py