Metadata-Version: 2.1
Name: simplarchiver
Version: 3.3
Summary: 一个简单的可扩展聚合异步下载器框架
Home-page: https://github.com/yindaheng98/simplarchiver
Author: yindaheng98
Author-email: yindaheng98@163.com
License: UNKNOWN
Platform: UNKNOWN
Classifier: Programming Language :: Python :: 3
Classifier: License :: OSI Approved :: MIT License
Classifier: Operating System :: OS Independent
License-File: LICENSE
